LICENSE.md
MANIFEST.in
README.md
setup.py
bernoulli/__init__.py
bernoulli/client_api.py
bernoulli.egg-info/PKG-INFO
bernoulli.egg-info/SOURCES.txt
bernoulli.egg-info/dependency_links.txt
bernoulli.egg-info/not-zip-safe
bernoulli.egg-info/requires.txt
bernoulli.egg-info/top_level.txt