Metadata-Version: 1.0
Name: bernoulli
Version: 0.1.3
Summary: A Python API for Bernoulli
Home-page: https://github.com/bernoulli-metrics/bernoulli-python
Author: Joe Gasiorek
Author-email: joe.gasiorek@gmail.com
License: MIT
Platform: UNKNOWN
